{
  "animateLoading": true,
  "autoGenerateForm": true,
  "backgroundColor": "#fff",
  "borderRadius": "{{appsmith.theme.borderRadius.appBorderRadius}}",
  "bottomRow": 81,
  "boxShadow": "none",
  "childStylesheet": {
    "ARRAY": {
      "accentColor": "{{appsmith.theme.colors.primaryColor}}",
      "borderRadius": "{{appsmith.theme.borderRadius.appBorderRadius}}",
      "boxShadow": "none",
      "cellBorderRadius": "{{appsmith.theme.borderRadius.appBorderRadius}}",
      "cellBoxShadow": "none"
    },
    "CHECKBOX": {
      "accentColor": "{{appsmith.theme.colors.primaryColor}}",
      "borderRadius": "{{appsmith.theme.borderRadius.appBorderRadius}}"
    },
    "CURRENCY_INPUT": {
      "accentColor": "{{appsmith.theme.colors.primaryColor}}",
      "borderRadius": "{{appsmith.theme.borderRadius.appBorderRadius}}",
      "boxShadow": "none"
    },
    "DATEPICKER": {
      "accentColor": "{{appsmith.theme.colors.primaryColor}}",
      "borderRadius": "{{appsmith.theme.borderRadius.appBorderRadius}}",
      "boxShadow": "none"
    },
    "EMAIL_INPUT": {
      "accentColor": "{{appsmith.theme.colors.primaryColor}}",
      "borderRadius": "{{appsmith.theme.borderRadius.appBorderRadius}}",
      "boxShadow": "none"
    },
    "MULTILINE_TEXT_INPUT": {
      "accentColor": "{{appsmith.theme.colors.primaryColor}}",
      "borderRadius": "{{appsmith.theme.borderRadius.appBorderRadius}}",
      "boxShadow": "none"
    },
    "MULTISELECT": {
      "accentColor": "{{appsmith.theme.colors.primaryColor}}",
      "borderRadius": "{{appsmith.theme.borderRadius.appBorderRadius}}",
      "boxShadow": "none"
    },
    "NUMBER_INPUT": {
      "accentColor": "{{appsmith.theme.colors.primaryColor}}",
      "borderRadius": "{{appsmith.theme.borderRadius.appBorderRadius}}",
      "boxShadow": "none"
    },
    "OBJECT": {
      "borderRadius": "{{appsmith.theme.borderRadius.appBorderRadius}}",
      "boxShadow": "none",
      "cellBorderRadius": "{{appsmith.theme.borderRadius.appBorderRadius}}",
      "cellBoxShadow": "none"
    },
    "PASSWORD_INPUT": {
      "accentColor": "{{appsmith.theme.colors.primaryColor}}",
      "borderRadius": "{{appsmith.theme.borderRadius.appBorderRadius}}",
      "boxShadow": "none"
    },
    "PHONE_NUMBER_INPUT": {
      "accentColor": "{{appsmith.theme.colors.primaryColor}}",
      "borderRadius": "{{appsmith.theme.borderRadius.appBorderRadius}}",
      "boxShadow": "none"
    },
    "RADIO_GROUP": {
      "accentColor": "{{appsmith.theme.colors.primaryColor}}",
      "boxShadow": "none"
    },
    "SELECT": {
      "accentColor": "{{appsmith.theme.colors.primaryColor}}",
      "borderRadius": "{{appsmith.theme.borderRadius.appBorderRadius}}",
      "boxShadow": "none"
    },
    "SWITCH": {
      "accentColor": "{{appsmith.theme.colors.primaryColor}}",
      "boxShadow": "none"
    },
    "TEXT_INPUT": {
      "accentColor": "{{appsmith.theme.colors.primaryColor}}",
      "borderRadius": "{{appsmith.theme.borderRadius.appBorderRadius}}",
      "boxShadow": "none"
    }
  },
  "disabledWhenInvalid": true,
  "displayName": "JSON Form",
  "dynamicBindingPathList": [
    {
      "key": "schema.__root_schema__.defaultValue"
    },
    {
      "key": "sourceData"
    },
    {
      "key": "schema.__root_schema__.borderRadius"
    },
    {
      "key": "schema.__root_schema__.cellBorderRadius"
    },
    {
      "key": "borderRadius"
    },
    {
      "key": "submitButtonStyles.buttonColor"
    },
    {
      "key": "submitButtonStyles.borderRadius"
    },
    {
      "key": "resetButtonStyles.borderRadius"
    },
    {
      "key": "resetButtonStyles.buttonColor"
    },
    {
      "key": "schema.__root_schema__.children.id.defaultValue"
    },
    {
      "key": "schema.__root_schema__.children.id.borderRadius"
    },
    {
      "key": "schema.__root_schema__.children.id.accentColor"
    },
    {
      "key": "schema.__root_schema__.children.role_id.defaultValue"
    },
    {
      "key": "schema.__root_schema__.children.role_id.borderRadius"
    },
    {
      "key": "schema.__root_schema__.children.role_id.accentColor"
    },
    {
      "key": "schema.__root_schema__.children.start_date.defaultValue"
    },
    {
      "key": "schema.__root_schema__.children.start_date.borderRadius"
    },
    {
      "key": "schema.__root_schema__.children.start_date.accentColor"
    },
    {
      "key": "schema.__root_schema__.children.end_date.defaultValue"
    },
    {
      "key": "schema.__root_schema__.children.end_date.borderRadius"
    },
    {
      "key": "schema.__root_schema__.children.end_date.accentColor"
    },
    {
      "key": "schema.__root_schema__.children.talent_id.defaultValue"
    },
    {
      "key": "schema.__root_schema__.children.talent_id.borderRadius"
    },
    {
      "key": "schema.__root_schema__.children.talent_id.accentColor"
    },
    {
      "key": "schema.__root_schema__.children.resume_detail.children.tenure.defaultValue"
    },
    {
      "key": "schema.__root_schema__.children.resume_detail.children.tenure.borderRadius"
    },
    {
      "key": "schema.__root_schema__.children.resume_detail.children.tenure.accentColor"
    },
    {
      "key": "schema.__root_schema__.children.resume_detail.children.company.defaultValue"
    },
    {
      "key": "schema.__root_schema__.children.resume_detail.children.company.borderRadius"
    },
    {
      "key": "schema.__root_schema__.children.resume_detail.children.company.accentColor"
    },
    {
      "key": "schema.__root_schema__.children.resume_detail.children.end_date.defaultValue"
    },
    {
      "key": "schema.__root_schema__.children.resume_detail.children.end_date.borderRadius"
    },
    {
      "key": "schema.__root_schema__.children.resume_detail.children.end_date.accentColor"
    },
    {
      "key": "schema.__root_schema__.children.resume_detail.children.location.defaultValue"
    },
    {
      "key": "schema.__root_schema__.children.resume_detail.children.location.borderRadius"
    },
    {
      "key": "schema.__root_schema__.children.resume_detail.children.location.accentColor"
    },
    {
      "key": "schema.__root_schema__.children.resume_detail.children.job_title.defaultValue"
    },
    {
      "key": "schema.__root_schema__.children.resume_detail.children.job_title.borderRadius"
    },
    {
      "key": "schema.__root_schema__.children.resume_detail.children.job_title.accentColor"
    },
    {
      "key": "schema.__root_schema__.children.resume_detail.children.start_date.defaultValue"
    },
    {
      "key": "schema.__root_schema__.children.resume_detail.children.start_date.borderRadius"
    },
    {
      "key": "schema.__root_schema__.children.resume_detail.children.start_date.accentColor"
    },
    {
      "key": "schema.__root_schema__.children.resume_detail.children.location_type.defaultValue"
    },
    {
      "key": "schema.__root_schema__.children.resume_detail.children.location_type.borderRadius"
    },
    {
      "key": "schema.__root_schema__.children.resume_detail.children.location_type.accentColor"
    },
    {
      "key": "schema.__root_schema__.children.resume_detail.children.employment_type.defaultValue"
    },
    {
      "key": "schema.__root_schema__.children.resume_detail.children.employment_type.borderRadius"
    },
    {
      "key": "schema.__root_schema__.children.resume_detail.children.employment_type.accentColor"
    },
    {
      "key": "schema.__root_schema__.children.resume_detail.children.responsibilities.defaultValue"
    },
    {
      "key": "schema.__root_schema__.children.resume_detail.children.responsibilities.borderRadius"
    },
    {
      "key": "schema.__root_schema__.children.resume_detail.children.responsibilities.accentColor"
    },
    {
      "key": "schema.__root_schema__.children.resume_detail.defaultValue"
    },
    {
      "key": "schema.__root_schema__.children.resume_detail.borderRadius"
    },
    {
      "key": "schema.__root_schema__.children.resume_detail.cellBorderRadius"
    },
    {
      "key": "schema.__root_schema__.children.created_at.defaultValue"
    },
    {
      "key": "schema.__root_schema__.children.created_at.borderRadius"
    },
    {
      "key": "schema.__root_schema__.children.created_at.accentColor"
    },
    {
      "key": "schema.__root_schema__.children.updated_at.defaultValue"
    },
    {
      "key": "schema.__root_schema__.children.updated_at.borderRadius"
    },
    {
      "key": "schema.__root_schema__.children.updated_at.accentColor"
    },
    {
      "key": "schema.__root_schema__.children.deleted_at.defaultValue"
    },
    {
      "key": "schema.__root_schema__.children.deleted_at.borderRadius"
    },
    {
      "key": "schema.__root_schema__.children.deleted_at.accentColor"
    },
    {
      "key": "schema.__root_schema__.children.index.defaultValue"
    },
    {
      "key": "schema.__root_schema__.children.index.borderRadius"
    },
    {
      "key": "schema.__root_schema__.children.index.accentColor"
    },
    {
      "key": "schema.__root_schema__.children.company_id.defaultValue"
    },
    {
      "key": "schema.__root_schema__.children.company_id.borderRadius"
    },
    {
      "key": "schema.__root_schema__.children.company_id.accentColor"
    }
  ],
  "dynamicHeight": "FIXED",
  "dynamicPropertyPathList": [
    {
      "key": "schema.__root_schema__.children.date_of_birth.defaultValue"
    },
    {
      "key": "onSubmit"
    },
    {
      "key": "schema.__root_schema__.children.start_date.defaultValue"
    },
    {
      "key": "schema.__root_schema__.children.end_date.defaultValue"
    }
  ],
  "dynamicTriggerPathList": [
    {
      "key": "onSubmit"
    }
  ],
  "fieldLimitExceeded": false,
  "fixedFooter": true,
  "hideCard": false,
  "iconSVG": "/static/media/icon.6bacf7df.svg",
  "isLoading": false,
  "isVisible": "true",
  "key": "h9l9ozr8op",
  "labelTextSize": "0.875rem",
  "leftColumn": 0,
  "maxDynamicHeight": 9000,
  "minDynamicHeight": 4,
  "onSubmit": "{{InsertQuery.run(\n\t() => SelectQuery.run()\n\t\t\t\t\t.then(() => closeModal('Insert_Modal')), \n\t(error) => showAlert(`Error while inserting resource!\\n ${error}`,'error'))\n}}",
  "parentColumnSpace": 8.125,
  "parentId": "9rhv3ioohq",
  "parentRowSpace": 10,
  "renderMode": "CANVAS",
  "resetButtonLabel": "Reset",
  "resetButtonStyles": {
    "borderRadius": "{{appsmith.theme.borderRadius.appBorderRadius}}",
    "boxShadow": "none",
    "buttonColor": "{{appsmith.theme.colors.primaryColor}}",
    "buttonVariant": "SECONDARY"
  },
  "rightColumn": 64,
  "schema": {
    "__root_schema__": {
      "accessor": "__root_schema__",
      "borderRadius": "{{appsmith.theme.borderRadius.appBorderRadius}}",
      "boxShadow": "none",
      "cellBorderRadius": "{{appsmith.theme.borderRadius.appBorderRadius}}",
      "cellBoxShadow": "none",
      "children": {
        "company_id": {
          "accentColor": "{{((sourceData, formData, fieldState) => ((appsmith.theme.colors.primaryColor)))(insert_form.sourceData, insert_form.formData, insert_form.fieldState)}}",
          "accessor": "company_id",
          "borderRadius": "{{((sourceData, formData, fieldState) => ((appsmith.theme.borderRadius.appBorderRadius)))(insert_form.sourceData, insert_form.formData, insert_form.fieldState)}}",
          "boxShadow": "none",
          "children": {},
          "dataType": "string",
          "defaultValue": "{{((sourceData, formData, fieldState) => (sourceData.company_id))(insert_form.sourceData, insert_form.formData, insert_form.fieldState)}}",
          "fieldType": "Text Input",
          "iconAlign": "left",
          "identifier": "company_id",
          "isCustomField": false,
          "isDisabled": false,
          "isRequired": false,
          "isSpellCheck": false,
          "isVisible": true,
          "label": "Company Id",
          "labelTextSize": "0.875rem",
          "originalIdentifier": "company_id",
          "position": 10,
          "sourceData": "muzmj37otl06w3up3l0qfwmu"
        },
        "created_at": {
          "accentColor": "{{((sourceData, formData, fieldState) => ((appsmith.theme.colors.primaryColor)))(insert_form.sourceData, insert_form.formData, insert_form.fieldState)}}",
          "accessor": "created_at",
          "borderRadius": "{{((sourceData, formData, fieldState) => ((appsmith.theme.borderRadius.appBorderRadius)))(insert_form.sourceData, insert_form.formData, insert_form.fieldState)}}",
          "boxShadow": "none",
          "children": {},
          "dataType": "string",
          "defaultValue": "{{((sourceData, formData, fieldState) => (sourceData.created_at))(insert_form.sourceData, insert_form.formData, insert_form.fieldState)}}",
          "fieldType": "Text Input",
          "iconAlign": "left",
          "identifier": "created_at",
          "isCustomField": false,
          "isDisabled": false,
          "isRequired": false,
          "isSpellCheck": false,
          "isVisible": true,
          "label": "Created At",
          "labelTextSize": "0.875rem",
          "originalIdentifier": "created_at",
          "position": 6,
          "sourceData": "2025-03-26T09:56:11Z"
        },
        "deleted_at": {
          "accentColor": "{{((sourceData, formData, fieldState) => ((appsmith.theme.colors.primaryColor)))(insert_form.sourceData, insert_form.formData, insert_form.fieldState)}}",
          "accessor": "deleted_at",
          "borderRadius": "{{((sourceData, formData, fieldState) => ((appsmith.theme.borderRadius.appBorderRadius)))(insert_form.sourceData, insert_form.formData, insert_form.fieldState)}}",
          "boxShadow": "none",
          "children": {},
          "dataType": "null",
          "defaultValue": "{{((sourceData, formData, fieldState) => (sourceData.deleted_at))(insert_form.sourceData, insert_form.formData, insert_form.fieldState)}}",
          "fieldType": "Text Input",
          "iconAlign": "left",
          "identifier": "deleted_at",
          "isCustomField": false,
          "isDisabled": false,
          "isRequired": false,
          "isSpellCheck": false,
          "isVisible": true,
          "label": "Deleted At",
          "labelTextSize": "0.875rem",
          "originalIdentifier": "deleted_at",
          "position": 8
        },
        "end_date": {
          "accentColor": "{{((sourceData, formData, fieldState) => ((appsmith.theme.colors.primaryColor)))(insert_form.sourceData, insert_form.formData, insert_form.fieldState)}}",
          "accessor": "end_date",
          "borderRadius": "{{((sourceData, formData, fieldState) => ((appsmith.theme.borderRadius.appBorderRadius)))(insert_form.sourceData, insert_form.formData, insert_form.fieldState)}}",
          "boxShadow": "none",
          "children": {},
          "closeOnSelection": false,
          "convertToISO": false,
          "dataType": "string",
          "dateFormat": "YYYY-MM-DD",
          "defaultValue": "{{((sourceData, formData, fieldState) => (moment(sourceData.end_date, \"YYYY-MM-DD\").format(\"YYYY-MM-DDTHH:mm:ss.sssZ\")))(insert_form.sourceData, insert_form.formData, insert_form.fieldState)}}",
          "fieldType": "Datepicker",
          "identifier": "end_date",
          "isCustomField": false,
          "isDisabled": false,
          "isRequired": false,
          "isVisible": true,
          "label": "End Date",
          "labelTextSize": "0.875rem",
          "maxDate": "2121-12-31T18:29:00.000Z",
          "minDate": "1920-12-31T18:30:00.000Z",
          "originalIdentifier": "end_date",
          "position": 3,
          "shortcuts": false,
          "sourceData": "2018-11-01",
          "timePrecision": "minute"
        },
        "id": {
          "accentColor": "{{((sourceData, formData, fieldState) => ((appsmith.theme.colors.primaryColor)))(insert_form.sourceData, insert_form.formData, insert_form.fieldState)}}",
          "accessor": "id",
          "borderRadius": "{{((sourceData, formData, fieldState) => ((appsmith.theme.borderRadius.appBorderRadius)))(insert_form.sourceData, insert_form.formData, insert_form.fieldState)}}",
          "boxShadow": "none",
          "children": {},
          "dataType": "string",
          "defaultValue": "{{((sourceData, formData, fieldState) => (sourceData.id))(insert_form.sourceData, insert_form.formData, insert_form.fieldState)}}",
          "fieldType": "Text Input",
          "iconAlign": "left",
          "identifier": "id",
          "isCustomField": false,
          "isDisabled": false,
          "isRequired": false,
          "isSpellCheck": false,
          "isVisible": true,
          "label": "Id",
          "labelTextSize": "0.875rem",
          "originalIdentifier": "id",
          "position": 0,
          "sourceData": "a0k6tax2w1zt7i8gewcb2k1v"
        },
        "index": {
          "accentColor": "{{((sourceData, formData, fieldState) => ((appsmith.theme.colors.primaryColor)))(insert_form.sourceData, insert_form.formData, insert_form.fieldState)}}",
          "accessor": "index",
          "borderRadius": "{{((sourceData, formData, fieldState) => ((appsmith.theme.borderRadius.appBorderRadius)))(insert_form.sourceData, insert_form.formData, insert_form.fieldState)}}",
          "boxShadow": "none",
          "children": {},
          "dataType": "number",
          "defaultValue": "{{((sourceData, formData, fieldState) => (sourceData.index))(insert_form.sourceData, insert_form.formData, insert_form.fieldState)}}",
          "fieldType": "Number Input",
          "iconAlign": "left",
          "identifier": "index",
          "isCustomField": false,
          "isDisabled": false,
          "isRequired": false,
          "isSpellCheck": false,
          "isVisible": true,
          "label": "Index",
          "labelTextSize": "0.875rem",
          "originalIdentifier": "index",
          "position": 9,
          "sourceData": 1
        },
        "resume_detail": {
          "accessor": "resume_detail",
          "borderRadius": "{{((sourceData, formData, fieldState) => ((appsmith.theme.borderRadius.appBorderRadius)))(insert_form.sourceData, insert_form.formData, insert_form.fieldState)}}",
          "boxShadow": "none",
          "cellBorderRadius": "{{((sourceData, formData, fieldState) => ((appsmith.theme.borderRadius.appBorderRadius)))(insert_form.sourceData, insert_form.formData, insert_form.fieldState)}}",
          "cellBoxShadow": "none",
          "children": {
            "company": {
              "accentColor": "{{((sourceData, formData, fieldState) => ((appsmith.theme.colors.primaryColor)))(insert_form.sourceData, insert_form.formData, insert_form.fieldState)}}",
              "accessor": "company",
              "borderRadius": "{{((sourceData, formData, fieldState) => ((appsmith.theme.borderRadius.appBorderRadius)))(insert_form.sourceData, insert_form.formData, insert_form.fieldState)}}",
              "boxShadow": "none",
              "children": {},
              "dataType": "string",
              "defaultValue": "{{((sourceData, formData, fieldState) => (sourceData.resume_detail.company))(insert_form.sourceData, insert_form.formData, insert_form.fieldState)}}",
              "fieldType": "Text Input",
              "iconAlign": "left",
              "identifier": "company",
              "isCustomField": false,
              "isDisabled": false,
              "isRequired": false,
              "isSpellCheck": false,
              "isVisible": true,
              "label": "Company",
              "labelTextSize": "0.875rem",
              "originalIdentifier": "company",
              "position": 1,
              "sourceData": "De Novo Corporate Services Limited"
            },
            "employment_type": {
              "accentColor": "{{((sourceData, formData, fieldState) => ((appsmith.theme.colors.primaryColor)))(insert_form.sourceData, insert_form.formData, insert_form.fieldState)}}",
              "accessor": "employment_type",
              "borderRadius": "{{((sourceData, formData, fieldState) => ((appsmith.theme.borderRadius.appBorderRadius)))(insert_form.sourceData, insert_form.formData, insert_form.fieldState)}}",
              "boxShadow": "none",
              "children": {},
              "dataType": "string",
              "defaultValue": "{{((sourceData, formData, fieldState) => (sourceData.resume_detail.employment_type))(insert_form.sourceData, insert_form.formData, insert_form.fieldState)}}",
              "fieldType": "Text Input",
              "iconAlign": "left",
              "identifier": "employment_type",
              "isCustomField": false,
              "isDisabled": false,
              "isRequired": false,
              "isSpellCheck": false,
              "isVisible": true,
              "label": "Employment Type",
              "labelTextSize": "0.875rem",
              "originalIdentifier": "employment_type",
              "position": 7,
              "sourceData": "Full Time"
            },
            "end_date": {
              "accentColor": "{{((sourceData, formData, fieldState) => ((appsmith.theme.colors.primaryColor)))(insert_form.sourceData, insert_form.formData, insert_form.fieldState)}}",
              "accessor": "end_date",
              "borderRadius": "{{((sourceData, formData, fieldState) => ((appsmith.theme.borderRadius.appBorderRadius)))(insert_form.sourceData, insert_form.formData, insert_form.fieldState)}}",
              "boxShadow": "none",
              "children": {},
              "dataType": "string",
              "defaultValue": "{{((sourceData, formData, fieldState) => (sourceData.resume_detail.end_date))(insert_form.sourceData, insert_form.formData, insert_form.fieldState)}}",
              "fieldType": "Text Input",
              "iconAlign": "left",
              "identifier": "end_date",
              "isCustomField": false,
              "isDisabled": false,
              "isRequired": false,
              "isSpellCheck": false,
              "isVisible": true,
              "label": "End Date",
              "labelTextSize": "0.875rem",
              "originalIdentifier": "end_date",
              "position": 2,
              "sourceData": "11/2018"
            },
            "job_title": {
              "accentColor": "{{((sourceData, formData, fieldState) => ((appsmith.theme.colors.primaryColor)))(insert_form.sourceData, insert_form.formData, insert_form.fieldState)}}",
              "accessor": "job_title",
              "borderRadius": "{{((sourceData, formData, fieldState) => ((appsmith.theme.borderRadius.appBorderRadius)))(insert_form.sourceData, insert_form.formData, insert_form.fieldState)}}",
              "boxShadow": "none",
              "children": {},
              "dataType": "string",
              "defaultValue": "{{((sourceData, formData, fieldState) => (sourceData.resume_detail.job_title))(insert_form.sourceData, insert_form.formData, insert_form.fieldState)}}",
              "fieldType": "Text Input",
              "iconAlign": "left",
              "identifier": "job_title",
              "isCustomField": false,
              "isDisabled": false,
              "isRequired": false,
              "isSpellCheck": false,
              "isVisible": true,
              "label": "Job Title",
              "labelTextSize": "0.875rem",
              "originalIdentifier": "job_title",
              "position": 4,
              "sourceData": "Assistant Project Manager"
            },
            "location": {
              "accentColor": "{{((sourceData, formData, fieldState) => ((appsmith.theme.colors.primaryColor)))(insert_form.sourceData, insert_form.formData, insert_form.fieldState)}}",
              "accessor": "location",
              "borderRadius": "{{((sourceData, formData, fieldState) => ((appsmith.theme.borderRadius.appBorderRadius)))(insert_form.sourceData, insert_form.formData, insert_form.fieldState)}}",
              "boxShadow": "none",
              "children": {},
              "dataType": "string",
              "defaultValue": "{{((sourceData, formData, fieldState) => (sourceData.resume_detail.location))(insert_form.sourceData, insert_form.formData, insert_form.fieldState)}}",
              "fieldType": "Text Input",
              "iconAlign": "left",
              "identifier": "location",
              "isCustomField": false,
              "isDisabled": false,
              "isRequired": false,
              "isSpellCheck": false,
              "isVisible": true,
              "label": "Location",
              "labelTextSize": "0.875rem",
              "originalIdentifier": "location",
              "position": 3,
              "sourceData": ""
            },
            "location_type": {
              "accentColor": "{{((sourceData, formData, fieldState) => ((appsmith.theme.colors.primaryColor)))(insert_form.sourceData, insert_form.formData, insert_form.fieldState)}}",
              "accessor": "location_type",
              "borderRadius": "{{((sourceData, formData, fieldState) => ((appsmith.theme.borderRadius.appBorderRadius)))(insert_form.sourceData, insert_form.formData, insert_form.fieldState)}}",
              "boxShadow": "none",
              "children": {},
              "dataType": "string",
              "defaultValue": "{{((sourceData, formData, fieldState) => (sourceData.resume_detail.location_type))(insert_form.sourceData, insert_form.formData, insert_form.fieldState)}}",
              "fieldType": "Text Input",
              "iconAlign": "left",
              "identifier": "location_type",
              "isCustomField": false,
              "isDisabled": false,
              "isRequired": false,
              "isSpellCheck": false,
              "isVisible": true,
              "label": "Location Type",
              "labelTextSize": "0.875rem",
              "originalIdentifier": "location_type",
              "position": 6,
              "sourceData": ""
            },
            "responsibilities": {
              "accentColor": "{{((sourceData, formData, fieldState) => ((appsmith.theme.colors.primaryColor)))(insert_form.sourceData, insert_form.formData, insert_form.fieldState)}}",
              "accessor": "responsibilities",
              "borderRadius": "{{((sourceData, formData, fieldState) => ((appsmith.theme.borderRadius.appBorderRadius)))(insert_form.sourceData, insert_form.formData, insert_form.fieldState)}}",
              "boxShadow": "none",
              "children": {},
              "dataType": "string",
              "defaultValue": "{{((sourceData, formData, fieldState) => (sourceData.resume_detail.responsibilities))(insert_form.sourceData, insert_form.formData, insert_form.fieldState)}}",
              "fieldType": "Text Input",
              "iconAlign": "left",
              "identifier": "responsibilities",
              "isCustomField": false,
              "isDisabled": false,
              "isRequired": false,
              "isSpellCheck": false,
              "isVisible": true,
              "label": "Responsibilities",
              "labelTextSize": "0.875rem",
              "originalIdentifier": "responsibilities",
              "position": 8,
              "sourceData": "Setting marketing plans and strategies. Producing financial online TV show in Guangzhou. Promoting the channel through social media including YouTube, Facebook, Weibo, Weixin."
            },
            "start_date": {
              "accentColor": "{{((sourceData, formData, fieldState) => ((appsmith.theme.colors.primaryColor)))(insert_form.sourceData, insert_form.formData, insert_form.fieldState)}}",
              "accessor": "start_date",
              "borderRadius": "{{((sourceData, formData, fieldState) => ((appsmith.theme.borderRadius.appBorderRadius)))(insert_form.sourceData, insert_form.formData, insert_form.fieldState)}}",
              "boxShadow": "none",
              "children": {},
              "dataType": "string",
              "defaultValue": "{{((sourceData, formData, fieldState) => (sourceData.resume_detail.start_date))(insert_form.sourceData, insert_form.formData, insert_form.fieldState)}}",
              "fieldType": "Text Input",
              "iconAlign": "left",
              "identifier": "start_date",
              "isCustomField": false,
              "isDisabled": false,
              "isRequired": false,
              "isSpellCheck": false,
              "isVisible": true,
              "label": "Start Date",
              "labelTextSize": "0.875rem",
              "originalIdentifier": "start_date",
              "position": 5,
              "sourceData": "05/2018"
            },
            "tenure": {
              "accentColor": "{{((sourceData, formData, fieldState) => ((appsmith.theme.colors.primaryColor)))(insert_form.sourceData, insert_form.formData, insert_form.fieldState)}}",
              "accessor": "tenure",
              "borderRadius": "{{((sourceData, formData, fieldState) => ((appsmith.theme.borderRadius.appBorderRadius)))(insert_form.sourceData, insert_form.formData, insert_form.fieldState)}}",
              "boxShadow": "none",
              "children": {},
              "dataType": "number",
              "defaultValue": "{{((sourceData, formData, fieldState) => (sourceData.resume_detail.tenure))(insert_form.sourceData, insert_form.formData, insert_form.fieldState)}}",
              "fieldType": "Number Input",
              "iconAlign": "left",
              "identifier": "tenure",
              "isCustomField": false,
              "isDisabled": false,
              "isRequired": false,
              "isSpellCheck": false,
              "isVisible": true,
              "label": "Tenure",
              "labelTextSize": "0.875rem",
              "originalIdentifier": "tenure",
              "position": 0,
              "sourceData": 0.5
            }
          },
          "dataType": "object",
          "defaultValue": "{{((sourceData, formData, fieldState) => (sourceData.resume_detail))(insert_form.sourceData, insert_form.formData, insert_form.fieldState)}}",
          "fieldType": "Object",
          "identifier": "resume_detail",
          "isCustomField": false,
          "isDisabled": false,
          "isRequired": false,
          "isVisible": true,
          "label": "Resume Detail",
          "labelTextSize": "0.875rem",
          "originalIdentifier": "resume_detail",
          "position": 5,
          "sourceData": {
            "company": "De Novo Corporate Services Limited",
            "employment_type": "Full Time",
            "end_date": "11/2018",
            "job_title": "Assistant Project Manager",
            "location": "",
            "location_type": "",
            "responsibilities": "Setting marketing plans and strategies. Producing financial online TV show in Guangzhou. Promoting the channel through social media including YouTube, Facebook, Weibo, Weixin.",
            "start_date": "05/2018",
            "tenure": 0.5
          }
        },
        "role_id": {
          "accentColor": "{{((sourceData, formData, fieldState) => ((appsmith.theme.colors.primaryColor)))(insert_form.sourceData, insert_form.formData, insert_form.fieldState)}}",
          "accessor": "role_id",
          "borderRadius": "{{((sourceData, formData, fieldState) => ((appsmith.theme.borderRadius.appBorderRadius)))(insert_form.sourceData, insert_form.formData, insert_form.fieldState)}}",
          "boxShadow": "none",
          "children": {},
          "dataType": "null",
          "defaultValue": "{{((sourceData, formData, fieldState) => (sourceData.role_id))(insert_form.sourceData, insert_form.formData, insert_form.fieldState)}}",
          "fieldType": "Text Input",
          "iconAlign": "left",
          "identifier": "role_id",
          "isCustomField": false,
          "isDisabled": false,
          "isRequired": false,
          "isSpellCheck": false,
          "isVisible": true,
          "label": "Role Id",
          "labelTextSize": "0.875rem",
          "originalIdentifier": "role_id",
          "position": 1
        },
        "start_date": {
          "accentColor": "{{((sourceData, formData, fieldState) => ((appsmith.theme.colors.primaryColor)))(insert_form.sourceData, insert_form.formData, insert_form.fieldState)}}",
          "accessor": "start_date",
          "borderRadius": "{{((sourceData, formData, fieldState) => ((appsmith.theme.borderRadius.appBorderRadius)))(insert_form.sourceData, insert_form.formData, insert_form.fieldState)}}",
          "boxShadow": "none",
          "children": {},
          "closeOnSelection": false,
          "convertToISO": false,
          "dataType": "string",
          "dateFormat": "YYYY-MM-DD",
          "defaultValue": "{{((sourceData, formData, fieldState) => (moment(sourceData.start_date, \"YYYY-MM-DD\").format(\"YYYY-MM-DDTHH:mm:ss.sssZ\")))(insert_form.sourceData, insert_form.formData, insert_form.fieldState)}}",
          "fieldType": "Datepicker",
          "identifier": "start_date",
          "isCustomField": false,
          "isDisabled": false,
          "isRequired": false,
          "isVisible": true,
          "label": "Start Date",
          "labelTextSize": "0.875rem",
          "maxDate": "2121-12-31T18:29:00.000Z",
          "minDate": "1920-12-31T18:30:00.000Z",
          "originalIdentifier": "start_date",
          "position": 2,
          "shortcuts": false,
          "sourceData": "2018-05-01",
          "timePrecision": "minute"
        },
        "talent_id": {
          "accentColor": "{{((sourceData, formData, fieldState) => ((appsmith.theme.colors.primaryColor)))(insert_form.sourceData, insert_form.formData, insert_form.fieldState)}}",
          "accessor": "talent_id",
          "borderRadius": "{{((sourceData, formData, fieldState) => ((appsmith.theme.borderRadius.appBorderRadius)))(insert_form.sourceData, insert_form.formData, insert_form.fieldState)}}",
          "boxShadow": "none",
          "children": {},
          "dataType": "string",
          "defaultValue": "{{((sourceData, formData, fieldState) => (sourceData.talent_id))(insert_form.sourceData, insert_form.formData, insert_form.fieldState)}}",
          "fieldType": "Text Input",
          "iconAlign": "left",
          "identifier": "talent_id",
          "isCustomField": false,
          "isDisabled": false,
          "isRequired": false,
          "isSpellCheck": false,
          "isVisible": true,
          "label": "Talent Id",
          "labelTextSize": "0.875rem",
          "originalIdentifier": "talent_id",
          "position": 4,
          "sourceData": "ay905zrhv4ep2f28qfj6l75f"
        },
        "updated_at": {
          "accentColor": "{{((sourceData, formData, fieldState) => ((appsmith.theme.colors.primaryColor)))(insert_form.sourceData, insert_form.formData, insert_form.fieldState)}}",
          "accessor": "updated_at",
          "borderRadius": "{{((sourceData, formData, fieldState) => ((appsmith.theme.borderRadius.appBorderRadius)))(insert_form.sourceData, insert_form.formData, insert_form.fieldState)}}",
          "boxShadow": "none",
          "children": {},
          "dataType": "string",
          "defaultValue": "{{((sourceData, formData, fieldState) => (sourceData.updated_at))(insert_form.sourceData, insert_form.formData, insert_form.fieldState)}}",
          "fieldType": "Text Input",
          "iconAlign": "left",
          "identifier": "updated_at",
          "isCustomField": false,
          "isDisabled": false,
          "isRequired": false,
          "isSpellCheck": false,
          "isVisible": true,
          "label": "Updated At",
          "labelTextSize": "0.875rem",
          "originalIdentifier": "updated_at",
          "position": 7,
          "sourceData": "2025-03-26T09:56:11Z"
        }
      },
      "dataType": "object",
      "defaultValue": "{{((sourceData, formData, fieldState) => (sourceData))(insert_form.sourceData, insert_form.formData, insert_form.fieldState)}}",
      "fieldType": "Object",
      "identifier": "__root_schema__",
      "isCustomField": false,
      "isDisabled": false,
      "isRequired": false,
      "isVisible": true,
      "label": "",
      "labelTextSize": "0.875rem",
      "originalIdentifier": "__root_schema__",
      "position": -1,
      "sourceData": {
        "col1": 5,
        "col2": "skill B",
        "col3": 9,
        "col4": true
      }
    }
  },
  "scrollContents": true,
  "showReset": true,
  "sourceData": "{{_.omit(data_table.tableData[0], \"customColumn1\", \"__primaryKey__\")}}",
  "submitButtonLabel": "Submit",
  "submitButtonStyles": {
    "borderRadius": "{{appsmith.theme.borderRadius.appBorderRadius}}",
    "boxShadow": "none",
    "buttonColor": "{{appsmith.theme.colors.primaryColor}}",
    "buttonVariant": "PRIMARY"
  },
  "title": "Insert Row",
  "topRow": 0,
  "type": "JSON_FORM_WIDGET",
  "version": 1,
  "widgetId": "o8oiq6vwkk",
  "widgetName": "insert_form"
}